{
	"configurations" : 
	[
		{
			"directories" : 
			[
				{
					"build" : ".",
					"hasInstallRule" : true,
					"jsonFile" : "directory-.-936626f0ce5df3cd31a2.json",
					"minimumCMakeVersion" : 
					{
						"string" : "3.12"
					},
					"projectIndex" : 0,
					"source" : ".",
					"targetIndexes" : 
					[
						0,
						1,
						2,
						3,
						4,
						5
					]
				}
			],
			"name" : "",
			"projects" : 
			[
				{
					"directoryIndexes" : 
					[
						0
					],
					"name" : "control_pkg",
					"targetIndexes" : 
					[
						0,
						1,
						2,
						3,
						4,
						5
					]
				}
			],
			"targets" : 
			[
				{
					"directoryIndex" : 0,
					"id" : "ament_cmake_python_build_control_pkg_egg::@6890427a1f51a3e7e1df",
					"jsonFile" : "target-ament_cmake_python_build_control_pkg_egg-98b5be4e4f2c4703ed5c.json",
					"name" : "ament_cmake_python_build_control_pkg_egg",
					"projectIndex" : 0
				},
				{
					"directoryIndex" : 0,
					"id" : "ament_cmake_python_copy_control_pkg::@6890427a1f51a3e7e1df",
					"jsonFile" : "target-ament_cmake_python_copy_control_pkg-f0dee48383ebc955ca33.json",
					"name" : "ament_cmake_python_copy_control_pkg",
					"projectIndex" : 0
				},
				{
					"directoryIndex" : 0,
					"id" : "control_pkg_uninstall::@6890427a1f51a3e7e1df",
					"jsonFile" : "target-control_pkg_uninstall-646316f2581979d7e8d2.json",
					"name" : "control_pkg_uninstall",
					"projectIndex" : 0
				},
				{
					"directoryIndex" : 0,
					"id" : "drivetrain::@6890427a1f51a3e7e1df",
					"jsonFile" : "target-drivetrain-c493e15f914981029daa.json",
					"name" : "drivetrain",
					"projectIndex" : 0
				},
				{
					"directoryIndex" : 0,
					"id" : "scoop::@6890427a1f51a3e7e1df",
					"jsonFile" : "target-scoop-d1764ea95d89c9f60da0.json",
					"name" : "scoop",
					"projectIndex" : 0
				},
				{
					"directoryIndex" : 0,
					"id" : "uninstall::@6890427a1f51a3e7e1df",
					"jsonFile" : "target-uninstall-bddc24c18fdc4d140115.json",
					"name" : "uninstall",
					"projectIndex" : 0
				}
			]
		}
	],
	"kind" : "codemodel",
	"paths" : 
	{
		"build" : "/home/catherineschuch/lunabotics_ros2_ws/build/control_pkg",
		"source" : "/home/catherineschuch/lunabotics_ros2_ws/src/control_pkg"
	},
	"version" : 
	{
		"major" : 2,
		"minor" : 3
	}
}
